LICENSE.rst
MANIFEST.in
README.rst
requirements.txt
requirements_dev.txt
requirements_test.txt
setup.py
ningen/__init__.py
ningen/capture.py
ningen/loop.py
ningen/value.py
ningen/writer.py
ningen.egg-info/PKG-INFO
ningen.egg-info/SOURCES.txt
ningen.egg-info/dependency_links.txt
ningen.egg-info/requires.txt
ningen.egg-info/top_level.txt
tests/__init__.py
tests/test_capture.py
tests/test_loop.py
tests/test_writer.py