Metadata-Version: 2.1
Name: ningen
Version: 0.4.0
Summary: Ninja Build Generation
Home-page: https://github.com/orenbenkiki/ningen.git
Author: Oren Ben-Kiki
Author-email: oren@ben-kiki.org
License: MIT license
Keywords: ninja,make
Platform: UNKNOWN
Classifier: Development Status :: 3 - Alpha
Classifier: Intended Audience :: Developers
Classifier: Natural Language :: English
Classifier: Programming Language :: Python :: 3
Classifier: Programming Language :: Python :: 3.7
Classifier: Programming Language :: Python :: 3.8
Classifier: Programming Language :: Python :: 3.9
Classifier: Programming Language :: Python :: 3.10
Requires-Python: >=3.7
Provides-Extra: dev
License-File: LICENSE.rst
